{"BlockIO":"16.4kB / 0B","CPUPerc":"0.00%","Container":"ebb3a33758d9f634dc7fcdf4898ec5e5391ab0cc3498fd43beb017e54b348663","ID":"ebb3a33758d9","MemPerc":"7.19%","MemUsage":"36.82MiB / 512MiB","Name":"temandifa_backend","NetIO":"92.7MB / 17.2MB","PIDs":"15"}
{"BlockIO":"51MB / 563MB","CPUPerc":"0.00%","Container":"1ec194d5b8020f6269174c22f5f0ad237397ab2c31b86dc2c395f92fda15c1f4","ID":"1ec194d5b802","MemPerc":"3.42%","MemUsage":"52.59MiB / 1.5GiB","Name":"temandifa_db","NetIO":"34.6MB / 50.7MB","PIDs":"8"}
{"BlockIO":"10.8MB / 2.14MB","CPUPerc":"0.32%","Container":"394562a6d02880fcf8b0c1db2385e6ac6cfa108ab28e1326eaab532cc2f30ee0","ID":"394562a6d028","MemPerc":"6.82%","MemUsage":"8.734MiB / 128MiB","Name":"temandifa_redis","NetIO":"32.3MB / 14.9MB","PIDs":"6"}
{"BlockIO":"495MB / 398MB","CPUPerc":"0.44%","Container":"93d0e2d4690b75fb85813ecff20d28a949420e31b63e735f8f023909e7f7c770","ID":"93d0e2d4690b","MemPerc":"27.06%","MemUsage":"277.1MiB / 1GiB","Name":"temandifa_ocr","NetIO":"78.5MB / 30.7MB","PIDs":"28"}
{"BlockIO":"594kB / 5.58MB","CPUPerc":"0.17%","Container":"1f0bb9cdfe4b69b085e665dc99bd9d1e392f9a0dd455be24dbf590f611008ce4","ID":"1f0bb9cdfe4b","MemPerc":"19.83%","MemUsage":"152.3MiB / 768MiB","Name":"temandifa_vision","NetIO":"11.1MB / 4.44MB","PIDs":"19"}
{"BlockIO":"177MB / 324MB","CPUPerc":"0.14%","Container":"c50e53d7f43ae18a82674dd8eb24faf8f489c4f350094a589a62898000295c48","ID":"c50e53d7f43a","MemPerc":"50.65%","MemUsage":"64.83MiB / 128MiB","Name":"temandifa_prometheus","NetIO":"1.38GB / 1.14GB","PIDs":"8"}
{"BlockIO":"78.6MB / 209kB","CPUPerc":"0.17%","Container":"2478766b4253cf506053e9e67d999adc0b10089285be055c17841430e1e895a7","ID":"2478766b4253","MemPerc":"24.65%","MemUsage":"315.5MiB / 1.25GiB","Name":"temandifa_speech","NetIO":"2.37MB / 47.8kB","PIDs":"22"}
{"BlockIO":"20.6GB / 12.4GB","CPUPerc":"0.93%","Container":"01e13737a92965e6b1a546c6f544390d20c4a247dcd79262585ea28a8aefa628","ID":"01e13737a929","MemPerc":"89.46%","MemUsage":"229MiB / 256MiB","Name":"temandifa_grafana","NetIO":"34.6MB / 1.16GB","PIDs":"23"}
{"BlockIO":"36.2MB / 1.11MB","CPUPerc":"0.06%","Container":"585021156ee332236705f127c5e531eb943c0962fc0007b3936ffac2d595dff8","ID":"585021156ee3","MemPerc":"35.60%","MemUsage":"22.79MiB / 64MiB","Name":"temandifa_alertmanager","NetIO":"9.34MB / 2.13MB","PIDs":"9"}